README.md
setup.py
TitanicClassifierCLI/__init__.py
TitanicClassifierCLI/cli.py
TitanicClassifierCLI/data_processor.py
TitanicClassifierCLI/evaluator.py
TitanicClassifierCLI/model_trainer.py
TitanicClassifierCLI.egg-info/PKG-INFO
TitanicClassifierCLI.egg-info/SOURCES.txt
TitanicClassifierCLI.egg-info/dependency_links.txt
TitanicClassifierCLI.egg-info/entry_points.txt
TitanicClassifierCLI.egg-info/requires.txt
TitanicClassifierCLI.egg-info/top_level.txt
tests/__init__.py
tests/test_cli.py
tests/test_data_processor.py
tests/test_evaluator.py
tests/test_model_trainer.py