Metadata-Version: 2.1
Name: TitanicClassifierCLI
Version: 0.2
Summary: A CLI tool for Titanic survival prediction
Home-page: https://github.com/tuusuario/TitanicClassifierCLI
Author: Jhon Felipe Delgado Dalazar
Author-email: jhonfeldel@gmail.com
Classifier: Programming Language :: Python :: 3
Classifier: License :: OSI Approved :: MIT License
Classifier: Operating System :: OS Independent
Requires-Python: >=3.7
Requires-Dist: Click
Requires-Dist: pandas
Requires-Dist: numpy
Requires-Dist: scikit-learn
Requires-Dist: matplotlib
Requires-Dist: seaborn
